MANIFEST.in
README.rst
setup.py
oneliners/__init__.py
oneliners.egg-info/PKG-INFO
oneliners.egg-info/SOURCES.txt
oneliners.egg-info/dependency_links.txt
oneliners.egg-info/not-zip-safe
oneliners.egg-info/top_level.txt
oneliners/data/chuck.txt.gz
oneliners/data/pyjokes_en.txt.gz
oneliners/data/unsorted.txt.gz