Metadata-Version: 1.1
Name: oneliners
Version: 1.0
Summary: A collection of random one-liner jokes scraped from the Internet.
Home-page: https://github.com/konstantint/oneliners
Author: Konstantin Tretyakov
Author-email: kt@ut.ee
License: MIT
Platform: UNKNOWN
Classifier: Development Status :: 7 - Inactive
